prefixcommons/__init__.py
prefixcommons/curie_transformer.py
prefixcommons/curie_util.py
prefixcommons/registry/idot_context.jsonld
prefixcommons/registry/monarch_context.jsonld
prefixcommons/registry/obo_context.jsonld
prefixcommons/registry/semweb_context.jsonld
prefixcommons/version.py
prefixcommons-0.1.11.dist-info/LICENSE
prefixcommons-0.1.11.dist-info/WHEEL
prefixcommons-0.1.11.dist-info/METADATA
prefixcommons-0.1.11.dist-info/RECORD
