Metadata-Version: 2.1
Name: prefixcommons
Version: 0.1.11
Summary: A python API for working with ID prefixes
Author: cmungall
Author-email: cjm@berkeleybop.org
Requires-Python: >=3.7,<4.0
Classifier: Programming Language :: Python :: 3
Classifier: Programming Language :: Python :: 3.10
Classifier: Programming Language :: Python :: 3.7
Classifier: Programming Language :: Python :: 3.8
Classifier: Programming Language :: Python :: 3.9
Requires-Dist: requests (>=2.28.1,<3.0.0)
